module_qc_analysis_tools/__init__.py
module_qc_analysis_tools/_version.py
module_qc_analysis_tools/analysis/__init__.py
module_qc_analysis_tools/analysis/adc_calibration.py
module_qc_analysis_tools/analysis/data_transmission.py
module_qc_analysis_tools/analysis/flatness.py
module_qc_analysis_tools/analysis/injection_capacitance.py
module_qc_analysis_tools/analysis/iv_measure.py
module_qc_analysis_tools/analysis/long_term_stability_dcs.py
module_qc_analysis_tools/analysis/ob_loaded_module_cell_envelope.py
module_qc_analysis_tools/analysis/ob_loaded_module_cell_metrology.py
module_qc_analysis_tools/analysis/quad_bare_module_metrology.py
module_qc_analysis_tools/analysis/quad_module_metrology.py
module_qc_analysis_tools/analysis/quad_pcb_metrology.py
module_qc_analysis_tools/analysis/sldo.py
module_qc_analysis_tools/analysis/wirebond_pull_test.py
module_qc_analysis_tools/analysis/wp_envelope.py
module_qc_analysis_tools/cli/ADC_CALIBRATION.py
module_qc_analysis_tools/cli/ANALOG_READBACK.py
module_qc_analysis_tools/cli/BARE_MODULE_SENSOR_IV.py
module_qc_analysis_tools/cli/DATA_TRANSMISSION.py
module_qc_analysis_tools/cli/ENVELOPE.py
module_qc_analysis_tools/cli/FLATNESS.py
module_qc_analysis_tools/cli/GENERIC_NONELEC.py
module_qc_analysis_tools/cli/HV_LV_TEST.py
module_qc_analysis_tools/cli/INJECTION_CAPACITANCE.py
module_qc_analysis_tools/cli/IV_MEASURE.py
module_qc_analysis_tools/cli/LAYER_THICKNESS.py
module_qc_analysis_tools/cli/LONG_TERM_STABILITY_DCS.py
module_qc_analysis_tools/cli/LP_MODE.py
module_qc_analysis_tools/cli/MASS_MEASUREMENT.py
module_qc_analysis_tools/cli/METROLOGY.py
module_qc_analysis_tools/cli/MIN_HEALTH_TEST.py
module_qc_analysis_tools/cli/OVERVOLTAGE_PROTECTION.py
module_qc_analysis_tools/cli/PIXEL_FAILURE_ANALYSIS.py
module_qc_analysis_tools/cli/QUAD_BARE_MODULE_METROLOGY.py
module_qc_analysis_tools/cli/QUAD_MODULE_METROLOGY.py
module_qc_analysis_tools/cli/SENSOR_TILE_IV_MEASURE.py
module_qc_analysis_tools/cli/SLDO.py
module_qc_analysis_tools-2.7.2.dist-info/METADATA
module_qc_analysis_tools-2.7.2.dist-info/WHEEL
module_qc_analysis_tools-2.7.2.dist-info/entry_points.txt
module_qc_analysis_tools-2.7.2.dist-info/licenses/LICENSE
module_qc_analysis_tools-2.7.2.dist-info/RECORD
