Metadata-Version: 2.4
Name: module-qc-analysis-tools
Version: 2.7.2
Summary: Module qc analysis tools
Project-URL: Homepage, https://gitlab.cern.ch/atlas-itk/pixel/module/module-qc-analysis-tools
Project-URL: Bug Tracker, https://gitlab.cern.ch/atlas-itk/pixel/module/module-qc-analysis-tools/-/issues
Project-URL: Source, https://gitlab.cern.ch/atlas-itk/pixel/module/module-qc-analysis-tools
Project-URL: Documentation, https://atlas-itk-pixel-mqat.docs.cern.ch/2.7/
Author-email: Jay Chan <jay.chan@cern.ch>
Maintainer-email: Giordon Stark <gstark@cern.ch>
License: Copyright (c) 2022 ATLAS ITk Pixel Modules
License-File: LICENSE
Classifier: License :: OSI Approved :: MIT License
Classifier: Operating System :: OS Independent
Classifier: Programming Language :: Python :: 3
Requires-Python: >=3.9
Requires-Dist: arrow
Requires-Dist: matplotlib
Requires-Dist: module-qc-data-tools>=1.4.0
Requires-Dist: module-qc-database-tools>=2.9.0
Requires-Dist: module-qc-tools>=2.7.1
Requires-Dist: numpy
Requires-Dist: scipy
Requires-Dist: typer>=0.18.0
